pyreporoot/__init__.py
pyreporoot/pyreporoot.py
py_repo_root-2.0.1.dist-info/LICENSE
py_repo_root-2.0.1.dist-info/METADATA
py_repo_root-2.0.1.dist-info/WHEEL
py_repo_root-2.0.1.dist-info/top_level.txt
py_repo_root-2.0.1.dist-info/RECORD
