Metadata-Version: 2.1
Name: py-repo-root
Version: 2.0.1
Summary: Python utility for cleaner handling of paths
Home-page: https://github.com/pashminacameron/py-repo-root
Author: Pashmina Cameron, Henry Jackson Flux, Andrew Fitzgibbon
Author-email: pashabhi@yahoo.com
License: MIT
Platform: UNKNOWN
Requires-Python: >=3.7.0
